{
  "hairColors": {
    "white": "#ffffff",
    "silver": "#cbd5e0",
    "blonde": "#fedc58",
    "brown": "#a56941",
    "black": "#592d3d",
    "red": "#e53e3e",
    "lightRed": "#feb2b2",
    "orange": "#f89e33",
    "lightOrange": "#fbd38d",
    "green": "#38a169",
    "lightGreen": "#9ae6b4",
    "turqoise": "#38b2ac",
    "lightTurqoise": "#81e6d9",
    "blue": "#3182ce",
    "lightBlue": "#bee3f8",
    "pink": "#ed64a6",
    "lightPink": "#fbb6ce",
    "purple": "#805ad5",
    "lightPurple": "#d6bcfa"
  },
  "hairColorGradients": {
    "white": ["#ffffff", "#e2e2e2"],
    "silver": ["#cbd5e0", "#a0aec0"],
    "blonde": ["#fedc58", "#edbf2e"],
    "brown": ["#a56941", "#8d5638"],
    "black": ["#592d3d", "#46202e"],
    "red": ["#e53e3e", "#c53030"],
    "lightRed": ["#feb2b2", "#fc8181"],
    "orange": ["#f89e33", "#dd6b20"],
    "lightOrange": ["#fbd38d", "#f6ad55"],
    "green": ["#38a169", "#2f855a"],
    "lightGreen": ["#9ae6b4", "#68d391"],
    "turqoise": ["#38b2ac", "#319795"],
    "lightTurqoise": ["#81e6d9", "#4fd1c5"],
    "blue": ["#3182ce", "#2b6cb0"],
    "lightBlue": ["#bee3f8", "#90cdf4"],
    "pink": ["#ed64a6", "#d53f8c"],
    "lightPink": ["#fbb6ce", "#f687b3"],
    "purple": ["#805ad5", "#6b46c1"],
    "lightPurple": ["#d6bcfa", "#b794f4"]
  },
  "clothingColors": {
    "white": "#ffffff",
    "gray": "#a0aec0",
    "black": "#633749",
    "red": "#e53e3e",
    "lightRed": "#feb2b2",
    "orange": "#f89e33",
    "lightOrange": "#fbd38d",
    "yellow": "#ecc94b",
    "lightYellow": "#faf089",
    "green": "#48bb78",
    "lightGreen": "#9ae6b4",
    "turqoise": "#38b2ac",
    "lightTurqoise": "#81e6d9",
    "blue": "#4299e1",
    "lightBlue": "#bee3f8",
    "pink": "#ed64a6",
    "lightPink": "#fbb6ce",
    "purple": "#9f7aea",
    "lightPurple": "#d6bcfa"
  },
  "hatColors": {
    "white": "#ffffff",
    "gray": "#a0aec0",
    "black": "#633749",
    "red": "#e53e3e",
    "lightRed": "#feb2b2",
    "orange": "#f89e33",
    "lightOrange": "#fbd38d",
    "yellow": "#ecc94b",
    "lightYellow": "#faf089",
    "green": "#48bb78",
    "lightGreen": "#9ae6b4",
    "turqoise": "#38b2ac",
    "lightTurqoise": "#81e6d9",
    "blue": "#4299e1",
    "lightBlue": "#bee3f8",
    "pink": "#ed64a6",
    "lightPink": "#fbb6ce",
    "purple": "#9f7aea",
    "lightPurple": "#d6bcfa"
  },
  "lipColors": {
    "red": "#e53e3e",
    "lightRed": "#feb2b2",
    "green": "#48bb78",
    "lightGreen": "#9ae6b4",
    "turqoise": "#38b2ac",
    "lightTurqoise": "#81e6d9",
    "blue": "#4299e1",
    "lightBlue": "#bee3f8",
    "pink": "#ed64a6",
    "lightPink": "#fbb6ce",
    "purple": "#9f7aea",
    "lightPurple": "#d6bcfa"
  },
  "backgroundColors": {
    "red": "#ed9191",
    "orange": "#f89e33",
    "yellow": "#f6e05e",
    "green": "#89d86f",
    "turqoise": "#4fd1c5",
    "blue": "#85c5e5",
    "pink": "#f687b3",
    "purple": "#b794f4",
    "none": "rgba(0,0,0,0)"
  },
  "skinColors": {
    "light": "#fdd2b2",
    "yellow": "#fbe8b3",
    "brown": "#d8985d",
    "dark": "#a56941",
    "red": "#cc734c",
    "black": "#754437"
  }
}
